tidal_gui/__init__.py
tidal_gui/downloader.py
tidal_gui/style.py
tidal_gui/theme.py
tidal_gui/control/__init__.py
tidal_gui/control/checkBox.py
tidal_gui/control/comboBox.py
tidal_gui/control/framelessWidget.py
tidal_gui/control/label.py
tidal_gui/control/layout.py
tidal_gui/control/line.py
tidal_gui/control/lineEdit.py
tidal_gui/control/listWidget.py
tidal_gui/control/pushButton.py
tidal_gui/control/scrollWidget.py
tidal_gui/control/tableView.py
tidal_gui/control/tableWidget.py
tidal_gui/resource/__init__.py
tidal_gui/resource/themeDefault.qss
tidal_gui/resource/svg/V.svg
tidal_gui/resource/svg/__init__.py
tidal_gui/resource/svg/buymeacoffee.svg
tidal_gui/resource/svg/check.svg
tidal_gui/resource/svg/down.svg
tidal_gui/resource/svg/downHover.svg
tidal_gui/resource/svg/github.svg
tidal_gui/resource/svg/left.svg
tidal_gui/resource/svg/paypal.svg
tidal_gui/resource/svg/right.svg
tidal_gui/resource/svg/search.svg
tidal_gui/resource/svg/search2.svg
tidal_gui/resource/svg/upHover.svg
tidal_gui/resource/svg/leftTab/download.svg
tidal_gui/resource/svg/leftTab/downloadHover.svg
tidal_gui/resource/svg/leftTab/info.svg
tidal_gui/resource/svg/leftTab/search.svg
tidal_gui/resource/svg/leftTab/settings.svg
tidal_gui/resource/svg/taskItem/cancel.svg
tidal_gui/resource/svg/taskItem/delete.svg
tidal_gui/resource/svg/taskItem/expand.svg
tidal_gui/resource/svg/taskItem/open.svg
tidal_gui/resource/svg/taskItem/retry.svg
tidal_gui/resource/svg/taskTab/complete.svg
tidal_gui/resource/svg/taskTab/download.svg
tidal_gui/resource/svg/taskTab/error.svg
tidal_gui/resource/svg/windows/close.svg
tidal_gui/resource/svg/windows/closeHover.svg
tidal_gui/resource/svg/windows/max.svg
tidal_gui/resource/svg/windows/min.svg
tidal_gui/resource/svg - 原/__init__.py
tidal_gui/view/__init__.py
tidal_gui/view/aboutView.py
tidal_gui/view/downloadItemView.py
tidal_gui/view/loginView.py
tidal_gui/view/mainView.py
tidal_gui/view/searchView.py
tidal_gui/view/settingsView.py
tidal_gui/view/taskItemView.py
tidal_gui-2022.1.18.3.dist-info/METADATA
tidal_gui-2022.1.18.3.dist-info/WHEEL
tidal_gui-2022.1.18.3.dist-info/entry_points.txt
tidal_gui-2022.1.18.3.dist-info/top_level.txt
tidal_gui-2022.1.18.3.dist-info/RECORD
