Metadata-Version: 2.1
Name: tidal-gui
Version: 2022.1.18.3
Summary: Tidal Music Downloader-GUI.
Home-page: UNKNOWN
Author: YaronH
Author-email: yaronhuang@foxmail.com
License: Apache2
Platform: any
Requires-Dist: tidal-dl
Requires-Dist: PyQt5
